proto/__init__.py
proto/proto/__init__.py
proto/proto/datasource/__init__.py
proto/proto/datasource/v1/__init__.py
proto/proto/datasource/v1/datasource_pb2.py
proto/proto/datasource/v1/datasource_pb2_grpc.py
aegis_proto-0.1.12.dist-info/METADATA
aegis_proto-0.1.12.dist-info/WHEEL
aegis_proto-0.1.12.dist-info/top_level.txt
aegis_proto-0.1.12.dist-info/RECORD
