Metadata-Version: 2.4
Name: aegis-proto
Version: 0.1.12
Summary: Aegis Platform Protobuf Definitions
Author-email: Aegis Team <dev@aegis-platform.io>
Classifier: Programming Language :: Python :: 3
Classifier: License :: OSI Approved :: MIT License
Requires-Python: >=3.8
Requires-Dist: grpcio>=1.60.0
Requires-Dist: protobuf>=4.25.0
